estatbr/__init__.py
estatbr/Alg_Linea/__init__.py
estatbr/Analise_Comb/__init__.py
estatbr/Grafico/__init__.py
estatbr/Probabilidade/__init__.py
estatbr-0.1.8.dist-info/LICENSE
estatbr-0.1.8.dist-info/METADATA
estatbr-0.1.8.dist-info/WHEEL
estatbr-0.1.8.dist-info/top_level.txt
estatbr-0.1.8.dist-info/RECORD
