Metadata-Version: 2.1
Name: estatbr
Version: 0.1.8
Summary: Uma biblioteca para Mudar sua experiencia em estatistica no python
Home-page: https://github.com/Anybosoft/Estatistica
Author: Samuel Bidjory
Author-email: bidjorys@gmail.com
License: UNKNOWN
Platform: UNKNOWN
Classifier: Development Status :: 3 - Alpha
Classifier: Intended Audience :: Developers
Classifier: License :: OSI Approved :: MIT License
Classifier: Programming Language :: Python :: 3
Classifier: Programming Language :: Python :: 3.6
Classifier: Programming Language :: Python :: 3.7
Classifier: Programming Language :: Python :: 3.8
Classifier: Programming Language :: Python :: 3.9
License-File: LICENSE
Requires-Dist: matplotlib
Requires-Dist: mpmath
Requires-Dist: numpy
Requires-Dist: scipy
Requires-Dist: sympy
